setup.py
RedisQ/BaseWorker.py
RedisQ/GPUWorker.py
RedisQ/WatchDog.py
RedisQ/__init__.py
RedisQ/entry_points.py
RedisQ.egg-info/PKG-INFO
RedisQ.egg-info/SOURCES.txt
RedisQ.egg-info/dependency_links.txt
RedisQ.egg-info/entry_points.txt
RedisQ.egg-info/not-zip-safe
RedisQ.egg-info/requires.txt
RedisQ.egg-info/top_level.txt
RedisQ/Base/Qjob.py
RedisQ/Base/Qlist.py
RedisQ/Base/__init__.py
RedisQ/Base/tools.py
RedisQ/scripts/DICOM_job_test.py
RedisQ/scripts/DICOMpayload.py
RedisQ/scripts/WSI_job_test.py
RedisQ/scripts/WSIpayload.py
RedisQ/scripts/__init__.py