Metadata-Version: 1.1
Name: RedisQ
Version: 1.5.8
Summary: a mini python Redis Task Queue model
Home-page: https://github.com/Tsimage/RedisQ
Author: Taylor
Author-email: tank357@icloud.com
License: GPL
Platform: UNKNOWN
Classifier: Development Status :: 3 - Alpha
Classifier: Environment :: Web Environment
Classifier: Intended Audience :: Developers
Classifier: Operating System :: OS Independent
Classifier: Programming Language :: Python :: 3.6
